MANIFEST.in
README
VERSION
ez_setup.py
setup.cfg
setup.py
DAV/AuthServer.py
DAV/BufferingHTTPServer.py
DAV/INI_Parse.py
DAV/WebDAVServer.py
DAV/__init__.py
DAV/constants.py
DAV/davcmd.py
DAV/davcopy.py
DAV/davmove.py
DAV/dbconn.py
DAV/delete.py
DAV/errors.py
DAV/iface.py
DAV/locks.py
DAV/propfind.py
DAV/report.py
DAV/status.py
DAV/utils.py
DAVServer/__init__.py
DAVServer/config.ini
DAVServer/daemonize.py
DAVServer/fileauth.py
DAVServer/fshandler.py
DAVServer/mysqlauth.py
DAVServer/server.py
PyWebDAV.egg-info/PKG-INFO
PyWebDAV.egg-info/SOURCES.txt
PyWebDAV.egg-info/dependency_links.txt
PyWebDAV.egg-info/entry_points.txt
PyWebDAV.egg-info/not-zip-safe
PyWebDAV.egg-info/top_level.txt
doc/ARCHITECTURE
doc/Changes
doc/Changes.rej
doc/INSTALL
doc/LICENSE
doc/TODO
doc/interface_class
doc/walker